kvdeveloper/__init__.py
kvdeveloper/__main__.py
kvdeveloper/build_config.py
kvdeveloper/cli.py
kvdeveloper/config.py
kvdeveloper/info_reader.py
kvdeveloper/module.py
kvdeveloper/utils.py
kvdeveloper/assets/css/github-markdown.css
kvdeveloper/assets/css/prism.css
kvdeveloper/assets/image_library/basic/discord128.png
kvdeveloper/assets/image_library/basic/discord256.png
kvdeveloper/assets/image_library/basic/discord512.png
kvdeveloper/assets/image_library/basic/discord64.png
kvdeveloper/assets/image_library/basic/discord720.png
kvdeveloper/assets/image_library/basic/google128.png
kvdeveloper/assets/image_library/basic/google256.png
kvdeveloper/assets/image_library/basic/google512.png
kvdeveloper/assets/image_library/basic/google64.png
kvdeveloper/assets/image_library/basic/google720.png
kvdeveloper/assets/image_library/basic/login_avatar128.png
kvdeveloper/assets/image_library/basic/login_illustration400.png
kvdeveloper/assets/image_library/basic/signup_avatar128.png
kvdeveloper/assets/image_library/basic/signup_illustration.png
kvdeveloper/assets/image_library/basic/stack_overflow128.png
kvdeveloper/assets/image_library/basic/stack_overflow256.png
kvdeveloper/assets/image_library/basic/stack_overflow512.png
kvdeveloper/assets/image_library/basic/stack_overflow64.png
kvdeveloper/assets/image_library/basic/stack_overflow720.png
kvdeveloper/assets/image_library/kvdeveloper/kvdeveloper_banner.png
kvdeveloper/assets/image_library/kvdeveloper/kvdeveloper_banner_outfit.png
kvdeveloper/assets/image_library/kvdeveloper/kvdeveloper_banner_outfit720.png
kvdeveloper/assets/image_library/kvdeveloper/kvdeveloper_banner_outfit_clear.png
kvdeveloper/assets/image_library/kvdeveloper/kvdeveloper_banner_outfit_clear512.png
kvdeveloper/assets/image_library/kvdeveloper/kvdeveloper_banner_outfit_clear720.png
kvdeveloper/assets/image_library/kvdeveloper/kvdeveloper_banner_zoom.png
kvdeveloper/assets/image_library/kvdeveloper/kvdeveloper_logo128.png
kvdeveloper-2025.0.0.dist-info/LICENSE
kvdeveloper-2025.0.0.dist-info/METADATA
kvdeveloper-2025.0.0.dist-info/WHEEL
kvdeveloper-2025.0.0.dist-info/entry_points.txt
kvdeveloper-2025.0.0.dist-info/top_level.txt
kvdeveloper-2025.0.0.dist-info/RECORD
