Metadata-Version: 2.2
Name: kvdeveloper
Version: 2025.0.0
Summary: KvDeveloper is a PyPI module designed to streamline the development of Kivy and KivyMD applications. Inspired by Expo CLI for React Native, KvDeveloper provides starter templates and essential functionalities to kickstart your projects with ease.
Author-email: Kartavya Shukla <novfensec@protonmail.com>
Maintainer-email: Kartavya Shukla <novfensec@protonmail.com>
License: MIT License
Project-URL: Homepage, https://github.com/Novfensec/KvDeveloper
Project-URL: Documentation, https://novfensec.github.io/KvDeveloper.docs
Project-URL: Repository, https://github.com/Novfensec/KvDeveloper
Project-URL: Bug Tracker, https://github.com/Novfensec/KvDeveloper/issues
Project-URL: Changelog, https://github.com/Novfensec/KvDeveloper/blob/main/CHANGELOG.md
Keywords: kivy,kivymd,open source,kvdeveloper,kartavya shukla,novfensec,kv
Classifier: Development Status :: 4 - Beta
Classifier: Intended Audience :: Developers
Classifier: Topic :: Software Development :: Build Tools
Classifier: License :: OSI Approved :: MIT License
Classifier: Programming Language :: Python :: 3
Requires-Python: >=3.9
License-File: LICENSE
Requires-Dist: kivy>=2.0.0
Requires-Dist: kivymd>=2.0.0
Requires-Dist: pillow>=10.0.0
Requires-Dist: typer>=0.12.3
Requires-Dist: rich>=13.7.1
Requires-Dist: requests>=2.32.0
Provides-Extra: all
Requires-Dist: markdown2; extra == "all"
Requires-Dist: pyqt5; extra == "all"
Requires-Dist: pyqtwebengine; extra == "all"
